zernike/__init__.py
zernike/pyramid.py
zernike/test.py
zernike/version.py
zernike-0.0.33.dist-info/LICENSE
zernike-0.0.33.dist-info/METADATA
zernike-0.0.33.dist-info/WHEEL
zernike-0.0.33.dist-info/top_level.txt
zernike-0.0.33.dist-info/RECORD
