Metadata-Version: 2.1
Name: zernike
Version: 0.0.33
Summary: Python code for Zernike polynomials
Home-page: https://github.com/jacopoantonello/zernike
Author: Jacopo Antonello
Author-email: jacopo@antonello.org
Classifier: Development Status :: 5 - Production/Stable
Classifier: Intended Audience :: Developers
Classifier: Topic :: Scientific/Engineering :: Physics
Classifier: License :: OSI Approved :: Apache Software License
Classifier: Programming Language :: Python :: 3
Requires-Python: >=2.7
License-File: LICENSE
Requires-Dist: numpy
Requires-Dist: h5py
Provides-Extra: plotting
Requires-Dist: matplotlib ; extra == 'plotting'
